{
    "subject": "p18615099",
    "study": "s56961814",
    "sequence": 6,
    "History": "Respiratory distress. Evaluate for pneumonia.",
    "Findings": "Single frontal portable view of the chest. Endotracheal tube terminates 42 cm above the carina. The side port of a nasogastric tube is below the diaphragm. Pulmonary vasculature is ill-defined, compatible with severe pulmonary edema. Hazy opacity overlying both lungs and blunting of the costophrenic angles are compatible with bilateral pleural effusions. No lobar consolidation or pneumothorax. Mild cardiomegaly is similar to prior. Leads of a left chest wall pacer terminates in the right atrium and ventricle. Median sternotomy wires and numerous mediastinal clips are intact.",
    "Impression": "Severe pulmonary edema with bilateral pleural effusions.",
    "annotations": "[{\"idx\": 0, \"sec\": \"HIST\", \"sent\": \"Respiratory distress. Evaluate for pneumonia.\", \"ent\": \"respiratory distress\", \"cat\": \"NCD\", \"status\": \"DP|\", \"rel\": {\"loc\": \"\", \"evd\": \"\"}, \"attr\": {\"appr\": \"\", \"level\": \"\", \"tmp\": \"\"}, \"OTH\": {\"hx\": \"\", \"source\": \"\", \"tech\": \"\", \"misc\": \"\"}}, {\"idx\": 1, \"sec\": \"HIST\", \"sent\": \"Evaluate for pneumonia.\", \"ent\": \"pneumonia\", \"cat\": \"CF\", \"status\": \"TP|evaluate for\", \"rel\": {\"loc\": \"\", \"evd\": \"\"}, \"attr\": {\"appr\": \"\", \"level\": \"\", \"tmp\": \"\"}, \"OTH\": {\"hx\": \"\", \"source\": \"\", \"tech\": \"\", \"misc\": \"\"}}, {\"idx\": 2, \"sec\": \"FIND\", \"sent\": \"Single frontal portable view of the chest.\", \"ent\": \"frontal portable view\", \"cat\": \"\", \"status\": \"DP|\", \"rel\": {\"loc\": \"loc1: chest\", \"evd\": \"\"}, \"attr\": {\"appr\": \"measure|single\", \"level\": \"\", \"tmp\": \"\"}, \"OTH\": {\"hx\": \"\", \"source\": \"\", \"tech\": \"\", \"misc\": \"\"}}, {\"idx\": 3, \"sec\": \"FIND\", \"sent\": \"Endotracheal tube terminates 42 cm above the carina.\", \"ent\": \"endotracheal tube\", \"cat\": \"OTH\", \"status\": \"DP|terminates\", \"rel\": {\"loc\": \"\", \"evd\": \"\"}, \"attr\": {\"appr\": \"measure|42 cm\", \"level\": \"\", \"tmp\": \"\"}, \"OTH\": {\"hx\": \"\", \"source\": \"\", \"tech\": \"\", \"misc\": \"\"}}, {\"idx\": 4, \"sec\": \"FIND\", \"sent\": \"The side port of a nasogastric tube is below the diaphragm.\", \"ent\": \"nasogastric tube\", \"cat\": \"OTH\", \"status\": \"DP|is below\", \"rel\": {\"loc\": \"loc1: diaphragm\", \"evd\": \"\"}, \"attr\": {\"appr\": \"\", \"level\": \"\", \"tmp\": \"\"}, \"OTH\": {\"hx\": \"\", \"source\": \"\", \"tech\": \"\", \"misc\": \"\"}}, {\"idx\": 5, \"sec\": \"FIND\", \"sent\": \"Pulmonary vasculature is ill-defined, compatible with severe pulmonary edema.\", \"ent\": \"vasculature\", \"cat\": \"LF\", \"status\": \"DP|ill-defined\", \"rel\": {\"loc\": \"\", \"evd\": \"\"}, \"attr\": {\"appr\": \"\", \"level\": \"sev|severe\", \"tmp\": \"\"}, \"OTH\": {\"hx\": \"\", \"source\": \"\", \"tech\": \"\", \"misc\": \"\"}}, {\"idx\": 6, \"sec\": \"FIND\", \"sent\": \"Pulmonary vasculature is ill-defined, compatible with severe pulmonary edema.\", \"ent\": \"pulmonary edema\", \"cat\": \"CF\", \"status\": \"DP|compatible with\", \"rel\": {\"loc\": \"\", \"evd\": \"pulmonary vasculature|idx5\"}, \"attr\": {\"appr\": \"\", \"level\": \"sev|severe\", \"tmp\": \"\"}, \"OTH\": {\"hx\": \"\", \"source\": \"\", \"tech\": \"\", \"misc\": \"\"}}, {\"idx\": 7, \"sec\": \"FIND\", \"sent\": \"Hazy opacity overlying both lungs and blunting of the costophrenic angles are compatible with bilateral pleural effusions.\", \"ent\": \"opacity\", \"cat\": \"LF\", \"status\": \"DP|overlying\", \"rel\": {\"loc\": \"loc1: both lungs\", \"evd\": \"\"}, \"attr\": {\"appr\": \"morph|hazy\", \"level\": \"\", \"tmp\": \"\"}, \"OTH\": {\"hx\": \"\", \"source\": \"\", \"tech\": \"\", \"misc\": \"\"}}, {\"idx\": 8, \"sec\": \"FIND\", \"sent\": \"Hazy opacity overlying both lungs and blunting of the costophrenic angles are compatible with bilateral pleural effusions.\", \"ent\": \"blunting\", \"cat\": \"LF\", \"status\": \"DP|blunting\", \"rel\": {\"loc\": \"\", \"evd\": \"\"}, \"attr\": {\"appr\": \"\", \"level\": \"\", \"tmp\": \"\"}, \"OTH\": {\"hx\": \"\", \"source\": \"\", \"tech\": \"\", \"misc\": \"\"}}, {\"idx\": 9, \"sec\": \"FIND\", \"sent\": \"Hazy opacity overlying both lungs and blunting of the costophrenic angles are compatible with bilateral pleural effusions.\", \"ent\": \"effusions\", \"cat\": \"PF\", \"status\": \"DP|compatible with\", \"rel\": {\"loc\": \"loc1: bilateral\", \"evd\": \"blunting of the costophrenic angles|idx8\"}, \"attr\": {\"appr\": \"\", \"level\": \"\", \"tmp\": \"\"}, \"OTH\": {\"hx\": \"\", \"source\": \"\", \"tech\": \"\", \"misc\": \"\"}}, {\"idx\": 10, \"sec\": \"FIND\", \"sent\": \"No lobar consolidation or pneumothorax.\", \"ent\": \"consolidation\", \"cat\": \"PF\", \"status\": \"DN|No\", \"rel\": {\"loc\": \"\", \"evd\": \"\"}, \"attr\": {\"appr\": \"\", \"level\": \"\", \"tmp\": \"\"}, \"OTH\": {\"hx\": \"\", \"source\": \"\", \"tech\": \"\", \"misc\": \"\"}}, {\"idx\": 11, \"sec\": \"FIND\", \"sent\": \"No lobar consolidation or pneumothorax.\", \"ent\": \"pneumothorax\", \"cat\": \"PF\", \"status\": \"DN|No\", \"rel\": {\"loc\": \"\", \"evd\": \"\"}, \"attr\": {\"appr\": \"\", \"level\": \"\", \"tmp\": \"\"}, \"OTH\": {\"hx\": \"\", \"source\": \"\", \"tech\": \"\", \"misc\": \"\"}}, {\"idx\": 12, \"sec\": \"FIND\", \"sent\": \"Mild cardiomegaly is similar to prior.\", \"ent\": \"cardiomegaly\", \"cat\": \"PF\", \"status\": \"DP|similar to prior\", \"rel\": {\"loc\": \"\", \"evd\": \"\"}, \"attr\": {\"appr\": \"\", \"level\": \"sev|mild\", \"tmp\": \"nchg|similar\"}, \"OTH\": {\"hx\": \"\", \"source\": \"\", \"tech\": \"\", \"misc\": \"\"}}, {\"idx\": 13, \"sec\": \"FIND\", \"sent\": \"Leads of a left chest wall pacer terminates in the right atrium and ventricle.\", \"ent\": \"leads\", \"cat\": \"OTH\", \"status\": \"DP|terminates\", \"rel\": {\"loc\": \"loc1: right atrium, det1: , loc2: ventricle, det2: \", \"evd\": \"\"}, \"attr\": {\"appr\": \"\", \"level\": \"\", \"tmp\": \"\"}, \"OTH\": {\"hx\": \"\", \"source\": \"\", \"tech\": \"\", \"misc\": \"\"}}, {\"idx\": 14, \"sec\": \"FIND\", \"sent\": \"Median sternotomy wires and numerous mediastinal clips are intact.\", \"ent\": \"median sternotomy wires\", \"cat\": \"OTH\", \"status\": \"DP|intact\", \"rel\": {\"loc\": \"\", \"evd\": \"\"}, \"attr\": {\"appr\": \"measure|numerous\", \"level\": \"\", \"tmp\": \"\"}, \"OTH\": {\"hx\": \"\", \"source\": \"\", \"tech\": \"\", \"misc\": \"\"}}, {\"idx\": 15, \"sec\": \"FIND\", \"sent\": \"Median sternotomy wires and numerous mediastinal clips are intact.\", \"ent\": \"mediastinal clips\", \"cat\": \"OTH\", \"status\": \"DP|intact\", \"rel\": {\"loc\": \"\", \"evd\": \"\"}, \"attr\": {\"appr\": \"measure|numerous\", \"level\": \"\", \"tmp\": \"\"}, \"OTH\": {\"hx\": \"\", \"source\": \"\", \"tech\": \"\", \"misc\": \"\"}}, {\"idx\": 16, \"sec\": \"IMPR\", \"sent\": \"Severe pulmonary edema with bilateral pleural effusions.\", \"ent\": \"pulmonary edema\", \"cat\": \"CF\", \"status\": \"DP|with\", \"rel\": {\"loc\": \"\", \"evd\": \"\"}, \"attr\": {\"appr\": \"\", \"level\": \"sev|severe\", \"tmp\": \"\"}, \"OTH\": {\"hx\": \"\", \"source\": \"\", \"tech\": \"\", \"misc\": \"\"}}, {\"idx\": 17, \"sec\": \"IMPR\", \"sent\": \"Severe pulmonary edema with bilateral pleural effusions.\", \"ent\": \"effusions\", \"cat\": \"PF\", \"status\": \"DP|with\", \"rel\": {\"loc\": \"loc1: bilateral\", \"evd\": \"\"}, \"attr\": {\"appr\": \"\", \"level\": \"\", \"tmp\": \"\"}, \"OTH\": {\"hx\": \"\", \"source\": \"\", \"tech\": \"\", \"misc\": \"\"}}]"
}