{
    "subject": "p13475033",
    "study": "s51820068",
    "sequence": 28,
    "History": "Chest pain and right basilar crackles, history of ILD, question superimposed pneumonia.",
    "Findings": "PA and lateral views of the chest were provided. As seen on multiple prior exams, there is generalized chronic interstitial fibrosis manifested by coarsened interstitial markings which is compatible with provided clinical history of ILD. There is no superimposed consolidation to suggest pneumonia. No pleural effusion or pneumothorax. The cardiomediastinal silhouette is stable. No free air below the right hemidiaphragm. An old left mid shaft clavicle deformity is again noted. No acute bony abnormalities.",
    "Impression": "No superimposed pneumonia in this patient with known ILD.",
    "annotations": "[{\"idx\": 0, \"sec\": \"HIST\", \"sent\": \"Chest pain and right basilar crackles, history of ILD, question superimposed pneumonia.\", \"ent\": \"chest pain\", \"cat\": \"SYM\", \"status\": \"DP|\", \"rel\": {\"loc\": \"\", \"evd\": \"\"}, \"attr\": {\"appr\": \"\", \"level\": \"\", \"tmp\": \"\"}, \"OTH\": {\"hx\": \"\", \"source\": \"\", \"tech\": \"\", \"misc\": \"\"}}, {\"idx\": 1, \"sec\": \"HIST\", \"sent\": \"Chest pain and right basilar crackles, history of ILD, question superimposed pneumonia.\", \"ent\": \"crackles\", \"cat\": \"COF\", \"status\": \"DP|\", \"rel\": {\"loc\": \"loc1: right basilar\", \"evd\": \"\"}, \"attr\": {\"appr\": \"\", \"level\": \"\", \"tmp\": \"\"}, \"OTH\": {\"hx\": \"\", \"source\": \"\", \"tech\": \"\", \"misc\": \"\"}}, {\"idx\": 2, \"sec\": \"HIST\", \"sent\": \"Chest pain and right basilar crackles, history of ILD, question superimposed pneumonia.\", \"ent\": \"ild\", \"cat\": \"CF\", \"status\": \"DP|history of\", \"rel\": {\"loc\": \"\", \"evd\": \"\"}, \"attr\": {\"appr\": \"\", \"level\": \"\", \"tmp\": \"\"}, \"OTH\": {\"hx\": \"history\", \"source\": \"\", \"tech\": \"\", \"misc\": \"\"}}, {\"idx\": 3, \"sec\": \"HIST\", \"sent\": \"Chest pain and right basilar crackles, history of ILD, question superimposed pneumonia.\", \"ent\": \"superimposed pneumonia\", \"cat\": \"CF\", \"status\": \"TP|question\", \"rel\": {\"loc\": \"\", \"evd\": \"\"}, \"attr\": {\"appr\": \"\", \"level\": \"\", \"tmp\": \"\"}, \"OTH\": {\"hx\": \"\", \"source\": \"\", \"tech\": \"\", \"misc\": \"\"}}, {\"idx\": 4, \"sec\": \"FIND\", \"sent\": \"PA and lateral views of the chest were provided.\", \"ent\": \"pa and lateral views\", \"cat\": \"\", \"status\": \"DP|provided\", \"rel\": {\"loc\": \"\", \"evd\": \"\"}, \"attr\": {\"appr\": \"\", \"level\": \"\", \"tmp\": \"\"}, \"OTH\": {\"hx\": \"\", \"source\": \"\", \"tech\": \"\", \"misc\": \"Chest x-ray\"}}, {\"idx\": 5, \"sec\": \"FIND\", \"sent\": \"As seen on multiple prior exams, there is generalized chronic interstitial fibrosis manifested by coarsened interstitial markings which is compatible with provided clinical history of ILD.\", \"ent\": \"interstitial fibrosis\", \"cat\": \"PF\", \"status\": \"DP|generalized chronic\", \"rel\": {\"loc\": \"\", \"evd\": \"interstitial markings|idx6\"}, \"attr\": {\"appr\": \"\", \"level\": \"\", \"tmp\": \"nchg|chronic\"}, \"OTH\": {\"hx\": \"history\", \"source\": \"\", \"tech\": \"\", \"misc\": \"Compatible with clinical history of ild\"}}, {\"idx\": 6, \"sec\": \"FIND\", \"sent\": \"As seen on multiple prior exams, there is generalized chronic interstitial fibrosis manifested by coarsened interstitial markings which is compatible with provided clinical history of ILD.\", \"ent\": \"interstitial markings\", \"cat\": \"LF\", \"status\": \"DP|coarsened\", \"rel\": {\"loc\": \"\", \"evd\": \"\"}, \"attr\": {\"appr\": \"morph|coarsened\", \"level\": \"\", \"tmp\": \"nchg|chronic\"}, \"OTH\": {\"hx\": \"history\", \"source\": \"\", \"tech\": \"\", \"misc\": \"\"}}, {\"idx\": 7, \"sec\": \"FIND\", \"sent\": \"There is no superimposed consolidation to suggest pneumonia.\", \"ent\": \"consolidation\", \"cat\": \"PF\", \"status\": \"DN|no superimposed\", \"rel\": {\"loc\": \"\", \"evd\": \"\"}, \"attr\": {\"appr\": \"\", \"level\": \"\", \"tmp\": \"\"}, \"OTH\": {\"hx\": \"\", \"source\": \"\", \"tech\": \"\", \"misc\": \"To suggest pneumonia\"}}, {\"idx\": 8, \"sec\": \"FIND\", \"sent\": \"No pleural effusion or pneumothorax.\", \"ent\": \"effusion\", \"cat\": \"PF\", \"status\": \"DN|No\", \"rel\": {\"loc\": \"\", \"evd\": \"\"}, \"attr\": {\"appr\": \"\", \"level\": \"\", \"tmp\": \"\"}, \"OTH\": {\"hx\": \"\", \"source\": \"\", \"tech\": \"\", \"misc\": \"\"}}, {\"idx\": 9, \"sec\": \"FIND\", \"sent\": \"No pleural effusion or pneumothorax.\", \"ent\": \"pneumothorax\", \"cat\": \"PF\", \"status\": \"DN|No\", \"rel\": {\"loc\": \"\", \"evd\": \"\"}, \"attr\": {\"appr\": \"\", \"level\": \"\", \"tmp\": \"\"}, \"OTH\": {\"hx\": \"\", \"source\": \"\", \"tech\": \"\", \"misc\": \"\"}}, {\"idx\": 10, \"sec\": \"FIND\", \"sent\": \"The cardiomediastinal silhouette is stable.\", \"ent\": \"silhouette\", \"cat\": \"LF\", \"status\": \"DP|stable\", \"rel\": {\"loc\": \"\", \"evd\": \"\"}, \"attr\": {\"appr\": \"\", \"level\": \"\", \"tmp\": \"nchg|stable\"}, \"OTH\": {\"hx\": \"\", \"source\": \"\", \"tech\": \"\", \"misc\": \"\"}}, {\"idx\": 11, \"sec\": \"FIND\", \"sent\": \"No free air below the right hemidiaphragm.\", \"ent\": \"free air\", \"cat\": \"PF\", \"status\": \"DN|No\", \"rel\": {\"loc\": \"loc1: right hemidiaphragm, det1: below\", \"evd\": \"\"}, \"attr\": {\"appr\": \"\", \"level\": \"\", \"tmp\": \"\"}, \"OTH\": {\"hx\": \"\", \"source\": \"\", \"tech\": \"\", \"misc\": \"\"}}, {\"idx\": 12, \"sec\": \"FIND\", \"sent\": \"An old left mid shaft clavicle deformity is again noted.\", \"ent\": \"deformity\", \"cat\": \"PF\", \"status\": \"DP|noted\", \"rel\": {\"loc\": \"loc1: left mid shaft\", \"evd\": \"\"}, \"attr\": {\"appr\": \"\", \"level\": \"\", \"tmp\": \"nchg|old\"}, \"OTH\": {\"hx\": \"\", \"source\": \"\", \"tech\": \"\", \"misc\": \"\"}}, {\"idx\": 13, \"sec\": \"FIND\", \"sent\": \"No acute bony abnormalities.\", \"ent\": \"abnormalities\", \"cat\": \"LF\", \"status\": \"DN|No acute\", \"rel\": {\"loc\": \"\", \"evd\": \"\"}, \"attr\": {\"appr\": \"\", \"level\": \"\", \"tmp\": \"emerge|acute\"}, \"OTH\": {\"hx\": \"\", \"source\": \"\", \"tech\": \"\", \"misc\": \"\"}}, {\"idx\": 14, \"sec\": \"IMPR\", \"sent\": \"No superimposed pneumonia in this patient with known ILD.\", \"ent\": \"superimposed pneumonia\", \"cat\": \"CF\", \"status\": \"DN|No\", \"rel\": {\"loc\": \"\", \"evd\": \"\"}, \"attr\": {\"appr\": \"\", \"level\": \"\", \"tmp\": \"\"}, \"OTH\": {\"hx\": \"history\", \"source\": \"\", \"tech\": \"\", \"misc\": \"\"}}]"
}