{
    "subject": "p12595991",
    "study": "s52170957",
    "sequence": 11,
    "History": "Year old woman with low lung volumes and resp distres overnight, evaluate for pulm edema.",
    "Findings": "",
    "Impression": "A small region of new opacification has developed at the lateral aspect of the right middle lobe. This could be early pneumonia. Lung volumes remain severely low, particularly the right lung above the elevated right hemidiaphragm which obscures a substantially consolidated right lower lobe, suffering from collapse or pneumonia P the condition of the left lower lobe is similar and. All of the basal pulmonary abnormalities have developed since. Moderate cardiomegaly is stable. Pleural effusions are presumed, but not substantial. Right internal jugular line ends close to the inferior cavoatrial junction. Transvenous atrial biventricular pacer defibrillator leads are continuous from the left pectoral generator, and unchanged. There is no pneumothorax.",
    "annotations": "[{\"idx\": 0, \"sec\": \"HIST\", \"sent\": \"Year old woman with low lung volumes and resp distres overnight, evaluate for pulm edema.\", \"ent\": \"low volumes\", \"cat\": \"\", \"status\": \"DP|\", \"rel\": {\"loc\": \"\", \"evd\": \"\"}, \"attr\": {\"appr\": \"\", \"level\": \"\", \"tmp\": \"\"}, \"OTH\": {\"hx\": \"\", \"source\": \"\", \"tech\": \"\", \"misc\": \"\"}}, {\"idx\": 1, \"sec\": \"HIST\", \"sent\": \"Year old woman with low lung volumes and resp distres overnight, evaluate for pulm edema.\", \"ent\": \"resp distres\", \"cat\": \"NCD\", \"status\": \"DP|\", \"rel\": {\"loc\": \"\", \"evd\": \"\"}, \"attr\": {\"appr\": \"\", \"level\": \"\", \"tmp\": \"\"}, \"OTH\": {\"hx\": \"\", \"source\": \"\", \"tech\": \"\", \"misc\": \"\"}}, {\"idx\": 2, \"sec\": \"HIST\", \"sent\": \"Year old woman with low lung volumes and resp distres overnight, evaluate for pulm edema.\", \"ent\": \"pulmonary edema\", \"cat\": \"CF\", \"status\": \"TP|evaluate for\", \"rel\": {\"loc\": \"\", \"evd\": \"\"}, \"attr\": {\"appr\": \"\", \"level\": \"\", \"tmp\": \"\"}, \"OTH\": {\"hx\": \"\", \"source\": \"\", \"tech\": \"\", \"misc\": \"\"}}, {\"idx\": 3, \"sec\": \"IMPR\", \"sent\": \"A small region of new opacification has developed at the lateral aspect of the right middle lobe.\", \"ent\": \"opacification\", \"cat\": \"LF\", \"status\": \"DP|has developed\", \"rel\": {\"loc\": \"loc1: right middle lobe\", \"evd\": \"\"}, \"attr\": {\"appr\": \"measure|small\", \"level\": \"\", \"tmp\": \"emerge|new\"}, \"OTH\": {\"hx\": \"\", \"source\": \"\", \"tech\": \"\", \"misc\": \"\"}}, {\"idx\": 4, \"sec\": \"IMPR\", \"sent\": \"This could be early pneumonia.\", \"ent\": \"pneumonia\", \"cat\": \"CF\", \"status\": \"TP|could be\", \"rel\": {\"loc\": \"loc1: right middle lobe\", \"evd\": \"opacification|idx3\"}, \"attr\": {\"appr\": \"\", \"level\": \"\", \"tmp\": \"emerge|early\"}, \"OTH\": {\"hx\": \"\", \"source\": \"\", \"tech\": \"\", \"misc\": \"\"}}, {\"idx\": 5, \"sec\": \"IMPR\", \"sent\": \"Lung volumes remain severely low, particularly the right lung above the elevated right hemidiaphragm which obscures a substantially consolidated right lower lobe, suffering from collapse or pneumonia.\", \"ent\": \"volumes\", \"cat\": \"LF\", \"status\": \"DP|remain\", \"rel\": {\"loc\": \"loc1: right lung\", \"evd\": \"\"}, \"attr\": {\"appr\": \"\", \"level\": \"sev|severely low\", \"tmp\": \"nchg|remain\"}, \"OTH\": {\"hx\": \"\", \"source\": \"\", \"tech\": \"\", \"misc\": \"\"}}, {\"idx\": 6, \"sec\": \"IMPR\", \"sent\": \"Lung volumes remain severely low, particularly the right lung above the elevated right hemidiaphragm which obscures a substantially consolidated right lower lobe, suffering from collapse or pneumonia.\", \"ent\": \"right hemidiaphragm\", \"cat\": \"LF\", \"status\": \"DP|elevated\", \"rel\": {\"loc\": \"loc1: right lung\", \"evd\": \"\"}, \"attr\": {\"appr\": \"\", \"level\": \"\", \"tmp\": \"\"}, \"OTH\": {\"hx\": \"\", \"source\": \"\", \"tech\": \"\", \"misc\": \"\"}}, {\"idx\": 7, \"sec\": \"IMPR\", \"sent\": \"Lung volumes remain severely low, particularly the right lung above the elevated right hemidiaphragm which obscures a substantially consolidated right lower lobe, suffering from collapse or pneumonia.\", \"ent\": \"consolidation\", \"cat\": \"PF\", \"status\": \"DP|substantially\", \"rel\": {\"loc\": \"loc1: right lower lobe\", \"evd\": \"\"}, \"attr\": {\"appr\": \"\", \"level\": \"\", \"tmp\": \"\"}, \"OTH\": {\"hx\": \"\", \"source\": \"\", \"tech\": \"\", \"misc\": \"\"}}, {\"idx\": 8, \"sec\": \"IMPR\", \"sent\": \"Lung volumes remain severely low, particularly the right lung above the elevated right hemidiaphragm which obscures a substantially consolidated right lower lobe, suffering from collapse or pneumonia.\", \"ent\": \"collapse\", \"cat\": \"LF\", \"status\": \"TP|suffering from\", \"rel\": {\"loc\": \"loc1: right lower lobe\", \"evd\": \"consolidation|idx7\"}, \"attr\": {\"appr\": \"\", \"level\": \"\", \"tmp\": \"\"}, \"OTH\": {\"hx\": \"\", \"source\": \"\", \"tech\": \"\", \"misc\": \"\"}}, {\"idx\": 9, \"sec\": \"IMPR\", \"sent\": \"Lung volumes remain severely low, particularly the right lung above the elevated right hemidiaphragm which obscures a substantially consolidated right lower lobe, suffering from collapse or pneumonia.\", \"ent\": \"pneumonia\", \"cat\": \"CF\", \"status\": \"TP|suffering from\", \"rel\": {\"loc\": \"loc1: right lower lobe\", \"evd\": \"consolidation|idx7\"}, \"attr\": {\"appr\": \"\", \"level\": \"\", \"tmp\": \"\"}, \"OTH\": {\"hx\": \"\", \"source\": \"\", \"tech\": \"\", \"misc\": \"\"}}, {\"idx\": 10, \"sec\": \"IMPR\", \"sent\": \"The condition of the left lower lobe is similar and.\", \"ent\": \"left lower lobe\", \"cat\": \"LF\", \"status\": \"DP|similar\", \"rel\": {\"loc\": \"loc1: left lower lobe\", \"evd\": \"\"}, \"attr\": {\"appr\": \"\", \"level\": \"\", \"tmp\": \"\"}, \"OTH\": {\"hx\": \"\", \"source\": \"\", \"tech\": \"\", \"misc\": \"\"}}, {\"idx\": 11, \"sec\": \"IMPR\", \"sent\": \"All of the basal pulmonary abnormalities have developed since.\", \"ent\": \"abnormalities\", \"cat\": \"LF\", \"status\": \"DP|have developed\", \"rel\": {\"loc\": \"\", \"evd\": \"\"}, \"attr\": {\"appr\": \"\", \"level\": \"\", \"tmp\": \"\"}, \"OTH\": {\"hx\": \"\", \"source\": \"\", \"tech\": \"\", \"misc\": \"\"}}, {\"idx\": 12, \"sec\": \"IMPR\", \"sent\": \"Moderate cardiomegaly is stable.\", \"ent\": \"cardiomegaly\", \"cat\": \"PF\", \"status\": \"DP|stable\", \"rel\": {\"loc\": \"\", \"evd\": \"\"}, \"attr\": {\"appr\": \"\", \"level\": \"sev|moderate\", \"tmp\": \"nchg|stable\"}, \"OTH\": {\"hx\": \"\", \"source\": \"\", \"tech\": \"\", \"misc\": \"\"}}, {\"idx\": 13, \"sec\": \"IMPR\", \"sent\": \"Pleural effusions are presumed, but not substantial.\", \"ent\": \"effusions\", \"cat\": \"PF\", \"status\": \"TP|presumed\", \"rel\": {\"loc\": \"\", \"evd\": \"\"}, \"attr\": {\"appr\": \"\", \"level\": \"sev|not substantial\", \"tmp\": \"\"}, \"OTH\": {\"hx\": \"\", \"source\": \"\", \"tech\": \"\", \"misc\": \"\"}}, {\"idx\": 14, \"sec\": \"IMPR\", \"sent\": \"Right internal jugular line ends close to the inferior cavoatrial junction.\", \"ent\": \"internal jugular line\", \"cat\": \"OTH\", \"status\": \"DP|ends\", \"rel\": {\"loc\": \"loc1: right\", \"evd\": \"\"}, \"attr\": {\"appr\": \"\", \"level\": \"\", \"tmp\": \"\"}, \"OTH\": {\"hx\": \"\", \"source\": \"\", \"tech\": \"\", \"misc\": \"Close to the inferior cavoatrial junction\"}}, {\"idx\": 15, \"sec\": \"IMPR\", \"sent\": \"Transvenous atrial biventricular pacer defibrillator leads are continuous from the left pectoral generator, and unchanged.\", \"ent\": \"transvenous atrial biventricular pacer defibrillator leads\", \"cat\": \"OTH\", \"status\": \"DP|continuous\", \"rel\": {\"loc\": \"loc1: left pectoral generator\", \"evd\": \"\"}, \"attr\": {\"appr\": \"\", \"level\": \"\", \"tmp\": \"nchg|unchanged\"}, \"OTH\": {\"hx\": \"\", \"source\": \"\", \"tech\": \"\", \"misc\": \"\"}}, {\"idx\": 16, \"sec\": \"IMPR\", \"sent\": \"There is no pneumothorax.\", \"ent\": \"pneumothorax\", \"cat\": \"PF\", \"status\": \"DN|no\", \"rel\": {\"loc\": \"\", \"evd\": \"\"}, \"attr\": {\"appr\": \"\", \"level\": \"\", \"tmp\": \"\"}, \"OTH\": {\"hx\": \"\", \"source\": \"\", \"tech\": \"\", \"misc\": \"\"}}]"
}