{
    "subject": "p16409152",
    "study": "s57478725",
    "sequence": 6,
    "History": "Adenocarcinoma, endotracheal tube placement.",
    "Findings": "As compared to the previous radiograph, the endotracheal tube is in unchanged position. The nasogastric tube and the right central venous access line are also unchanged. There are bilaterally increasing pleural effusions with subsequent increasing areas of basal atelectasis. The overall lung volumes remain low. Moderate cardiomegaly is unchanged. Known pulmonary metastatic disease.",
    "Impression": "",
    "annotations": "[{\"idx\": 0, \"sec\": \"HIST\", \"sent\": \"Adenocarcinoma, endotracheal tube placement.\", \"ent\": \"adenocarcinoma\", \"cat\": \"CF\", \"status\": \"DP|\", \"rel\": {\"loc\": \"\", \"evd\": \"\"}, \"attr\": {\"appr\": \"\", \"level\": \"\", \"tmp\": \"\"}, \"OTH\": {\"hx\": \"\", \"source\": \"\", \"tech\": \"\", \"misc\": \"\"}}, {\"idx\": 1, \"sec\": \"HIST\", \"sent\": \"Adenocarcinoma, endotracheal tube placement.\", \"ent\": \"endotracheal tube\", \"cat\": \"OTH\", \"status\": \"DP|\", \"rel\": {\"loc\": \"\", \"evd\": \"\"}, \"attr\": {\"appr\": \"\", \"level\": \"\", \"tmp\": \"\"}, \"OTH\": {\"hx\": \"\", \"source\": \"\", \"tech\": \"\", \"misc\": \"\"}}, {\"idx\": 2, \"sec\": \"FIND\", \"sent\": \"As compared to the previous radiograph, the endotracheal tube is in unchanged position.\", \"ent\": \"endotracheal tube\", \"cat\": \"OTH\", \"status\": \"DN|unchanged position\", \"rel\": {\"loc\": \"\", \"evd\": \"\"}, \"attr\": {\"appr\": \"\", \"level\": \"\", \"tmp\": \"nchg|unchanged\"}, \"OTH\": {\"hx\": \"\", \"source\": \"\", \"tech\": \"\", \"misc\": \"\"}}, {\"idx\": 3, \"sec\": \"FIND\", \"sent\": \"The nasogastric tube and the right central venous access line are also unchanged.\", \"ent\": \"nasogastric tube\", \"cat\": \"OTH\", \"status\": \"DN|unchanged\", \"rel\": {\"loc\": \"\", \"evd\": \"\"}, \"attr\": {\"appr\": \"\", \"level\": \"\", \"tmp\": \"nchg|unchanged\"}, \"OTH\": {\"hx\": \"\", \"source\": \"\", \"tech\": \"\", \"misc\": \"\"}}, {\"idx\": 4, \"sec\": \"FIND\", \"sent\": \"The nasogastric tube and the right central venous access line are also unchanged.\", \"ent\": \"central venous access line\", \"cat\": \"OTH\", \"status\": \"DN|unchanged\", \"rel\": {\"loc\": \"loc1: right\", \"evd\": \"\"}, \"attr\": {\"appr\": \"\", \"level\": \"\", \"tmp\": \"nchg|unchanged\"}, \"OTH\": {\"hx\": \"\", \"source\": \"\", \"tech\": \"\", \"misc\": \"\"}}, {\"idx\": 5, \"sec\": \"FIND\", \"sent\": \"There are bilaterally increasing pleural effusions with subsequent increasing areas of basal atelectasis.\", \"ent\": \"effusions\", \"cat\": \"PF\", \"status\": \"DP|increasing\", \"rel\": {\"loc\": \"loc1: bilaterally\", \"evd\": \"\"}, \"attr\": {\"appr\": \"\", \"level\": \"\", \"tmp\": \"worsened|increasing\"}, \"OTH\": {\"hx\": \"\", \"source\": \"\", \"tech\": \"\", \"misc\": \"\"}}, {\"idx\": 6, \"sec\": \"FIND\", \"sent\": \"There are bilaterally increasing pleural effusions with subsequent increasing areas of basal atelectasis.\", \"ent\": \"atelectasis\", \"cat\": \"PF\", \"status\": \"DP|increasing\", \"rel\": {\"loc\": \"loc1: basal\", \"evd\": \"pleural effusions|idx5\"}, \"attr\": {\"appr\": \"\", \"level\": \"\", \"tmp\": \"worsened|increasing\"}, \"OTH\": {\"hx\": \"\", \"source\": \"\", \"tech\": \"\", \"misc\": \"\"}}, {\"idx\": 7, \"sec\": \"FIND\", \"sent\": \"The overall lung volumes remain low.\", \"ent\": \"volumes\", \"cat\": \"LF\", \"status\": \"DN|low\", \"rel\": {\"loc\": \"\", \"evd\": \"\"}, \"attr\": {\"appr\": \"measure|low\", \"level\": \"\", \"tmp\": \"nchg|remain\"}, \"OTH\": {\"hx\": \"\", \"source\": \"\", \"tech\": \"\", \"misc\": \"\"}}, {\"idx\": 8, \"sec\": \"FIND\", \"sent\": \"Moderate cardiomegaly is unchanged.\", \"ent\": \"cardiomegaly\", \"cat\": \"PF\", \"status\": \"DN|unchanged\", \"rel\": {\"loc\": \"\", \"evd\": \"\"}, \"attr\": {\"appr\": \"\", \"level\": \"sev|moderate\", \"tmp\": \"nchg|unchanged\"}, \"OTH\": {\"hx\": \"\", \"source\": \"\", \"tech\": \"\", \"misc\": \"\"}}, {\"idx\": 9, \"sec\": \"FIND\", \"sent\": \"Known pulmonary metastatic disease.\", \"ent\": \"metastatic disease\", \"cat\": \"CF\", \"status\": \"DP|known\", \"rel\": {\"loc\": \"\", \"evd\": \"\"}, \"attr\": {\"appr\": \"\", \"level\": \"\", \"tmp\": \"\"}, \"OTH\": {\"hx\": \"\", \"source\": \"\", \"tech\": \"\", \"misc\": \"\"}}]"
}