{
    "subject": "p12185775",
    "study": "s53923012",
    "sequence": 8,
    "History": "Evaluation of patient with history of kidney transplant and heart failure for interval change.",
    "Findings": "Again visualized is a stable right lower lobe opacity consistent with small to moderate right pleural effusion. Improved asymmetric edema is noted on the left. There is no evidence of new consolidation or pneumothorax. Cardiomediastinal silhouette remains stable. Osseous structures remain normal.",
    "Impression": "Stable small to moderal right pleural effusion. Improved asymmetric edema is noted on the left.",
    "annotations": "[{\"idx\": 0, \"sec\": \"HIST\", \"sent\": \"Evaluation of patient with history of kidney transplant and heart failure for interval change.\", \"ent\": \"kidney transplant\", \"cat\": \"OTH\", \"status\": \"DP|history of\", \"rel\": {\"loc\": \"\", \"evd\": \"\"}, \"attr\": {\"appr\": \"\", \"level\": \"\", \"tmp\": \"\"}, \"OTH\": {\"hx\": \"history\", \"source\": \"\", \"tech\": \"\", \"misc\": \"\"}}, {\"idx\": 1, \"sec\": \"HIST\", \"sent\": \"Evaluation of patient with history of kidney transplant and heart failure for interval change.\", \"ent\": \"heart failure\", \"cat\": \"CF\", \"status\": \"DP|history of\", \"rel\": {\"loc\": \"\", \"evd\": \"\"}, \"attr\": {\"appr\": \"\", \"level\": \"\", \"tmp\": \"\"}, \"OTH\": {\"hx\": \"history\", \"source\": \"\", \"tech\": \"\", \"misc\": \"\"}}, {\"idx\": 2, \"sec\": \"FIND\", \"sent\": \"Again visualized is a stable right lower lobe opacity consistent with small to moderate right pleural effusion.\", \"ent\": \"opacity\", \"cat\": \"LF\", \"status\": \"DP|visualized\", \"rel\": {\"loc\": \"loc1: right lower lobe\", \"evd\": \"\"}, \"attr\": {\"appr\": \"\", \"level\": \"\", \"tmp\": \"nchg|stable\"}, \"OTH\": {\"hx\": \"\", \"source\": \"\", \"tech\": \"\", \"misc\": \"\"}}, {\"idx\": 3, \"sec\": \"FIND\", \"sent\": \"Again visualized is a stable right lower lobe opacity consistent with small to moderate right pleural effusion.\", \"ent\": \"effusion\", \"cat\": \"PF\", \"status\": \"DP|consistent with\", \"rel\": {\"loc\": \"loc1: right lower lobe\", \"evd\": \"opacity|idx2\"}, \"attr\": {\"appr\": \"\", \"level\": \"sev|small to moderate\", \"tmp\": \"nchg|stable\"}, \"OTH\": {\"hx\": \"\", \"source\": \"\", \"tech\": \"\", \"misc\": \"\"}}, {\"idx\": 4, \"sec\": \"FIND\", \"sent\": \"Improved asymmetric edema is noted on the left.\", \"ent\": \"edema\", \"cat\": \"CF\", \"status\": \"DP|noted\", \"rel\": {\"loc\": \"loc1: left\", \"evd\": \"\"}, \"attr\": {\"appr\": \"\", \"level\": \"\", \"tmp\": \"impr|improved\"}, \"OTH\": {\"hx\": \"\", \"source\": \"\", \"tech\": \"\", \"misc\": \"Asymmetric\"}}, {\"idx\": 5, \"sec\": \"FIND\", \"sent\": \"There is no evidence of new consolidation or pneumothorax.\", \"ent\": \"consolidation\", \"cat\": \"PF\", \"status\": \"DN|no evidence of\", \"rel\": {\"loc\": \"\", \"evd\": \"\"}, \"attr\": {\"appr\": \"\", \"level\": \"\", \"tmp\": \"emerge|new\"}, \"OTH\": {\"hx\": \"\", \"source\": \"\", \"tech\": \"\", \"misc\": \"\"}}, {\"idx\": 6, \"sec\": \"FIND\", \"sent\": \"There is no evidence of new consolidation or pneumothorax.\", \"ent\": \"pneumothorax\", \"cat\": \"PF\", \"status\": \"DN|no evidence of\", \"rel\": {\"loc\": \"\", \"evd\": \"\"}, \"attr\": {\"appr\": \"\", \"level\": \"\", \"tmp\": \"emerge|new\"}, \"OTH\": {\"hx\": \"\", \"source\": \"\", \"tech\": \"\", \"misc\": \"\"}}, {\"idx\": 7, \"sec\": \"FIND\", \"sent\": \"Cardiomediastinal silhouette remains stable.\", \"ent\": \"silhouette\", \"cat\": \"LF\", \"status\": \"DP|remains\", \"rel\": {\"loc\": \"\", \"evd\": \"\"}, \"attr\": {\"appr\": \"\", \"level\": \"\", \"tmp\": \"nchg|stable\"}, \"OTH\": {\"hx\": \"\", \"source\": \"\", \"tech\": \"\", \"misc\": \"\"}}, {\"idx\": 8, \"sec\": \"FIND\", \"sent\": \"Osseous structures remain normal.\", \"ent\": \"osseous structures\", \"cat\": \"LF\", \"status\": \"DP|remain\", \"rel\": {\"loc\": \"\", \"evd\": \"\"}, \"attr\": {\"appr\": \"morph|normal\", \"level\": \"\", \"tmp\": \"\"}, \"OTH\": {\"hx\": \"\", \"source\": \"\", \"tech\": \"\", \"misc\": \"\"}}, {\"idx\": 9, \"sec\": \"IMPR\", \"sent\": \"Stable small to moderate right pleural effusion.\", \"ent\": \"effusion\", \"cat\": \"PF\", \"status\": \"DP|stable\", \"rel\": {\"loc\": \"loc1: right\", \"evd\": \"\"}, \"attr\": {\"appr\": \"\", \"level\": \"sev|small to moderate\", \"tmp\": \"nchg|stable\"}, \"OTH\": {\"hx\": \"\", \"source\": \"\", \"tech\": \"\", \"misc\": \"\"}}, {\"idx\": 10, \"sec\": \"IMPR\", \"sent\": \"Improved asymmetric edema is noted on the left.\", \"ent\": \"edema\", \"cat\": \"CF\", \"status\": \"DP|noted\", \"rel\": {\"loc\": \"loc1: left\", \"evd\": \"\"}, \"attr\": {\"appr\": \"\", \"level\": \"\", \"tmp\": \"impr|improved\"}, \"OTH\": {\"hx\": \"\", \"source\": \"\", \"tech\": \"\", \"misc\": \"Asymmetric\"}}]"
}